{
    "nama_sistem": "TEQARA Enterprise v2.0",
    "deskripsi": "Platform Penjualan Komputer & Gadget Terintegrasi",
    "versi_laravel": "12.50.0",
    "bahasa_sistem": "100% Bahasa Indonesia",
    "status_arsitektur": "SPA (Single Page Application) via Livewire",
    "kebijakan_ui": "0% Modal (Mutlak)",
    "waktu_pembaruan_terakhir": "05/02/2026 17:15:20",
    "statistik_data": {
        "pengguna": 11,
        "produk": 2,
        "pesanan": 0,
        "log_aktivitas": 0,
        "voucher": 0,
        "ulasan": 0
    },
    "modul_aktif": {
        "Hulu": [
            "Manajemen Produk Kompleks",
            "Varian SKU",
            "Gudang & Stok",
            "Kategori & Merek"
        ],
        "Tengah": [
            "Katalog Spotlight",
            "Detail Produk Rich-Media",
            "Keranjang Persisten",
            "Voucher Promo"
        ],
        "Hilir": [
            "Checkout Multiproses",
            "Gateway Pembayaran Simulasi",
            "Timeline Pelacakan",
            "Audit Log Naratif"
        ]
    },
    "daftar_endpoint": [
        {
            "uri": "livewire-f552b613/update",
            "nama": "default.livewire.update",
            "metode": "POST"
        },
        {
            "uri": "livewire-f552b613/livewire.js",
            "nama": null,
            "metode": "GET|HEAD"
        },
        {
            "uri": "livewire-f552b613/livewire.min.js.map",
            "nama": null,
            "metode": "GET|HEAD"
        },
        {
            "uri": "livewire-f552b613/livewire.csp.min.js.map",
            "nama": null,
            "metode": "GET|HEAD"
        },
        {
            "uri": "livewire-f552b613/upload-file",
            "nama": "livewire.upload-file",
            "metode": "POST"
        },
        {
            "uri": "livewire-f552b613/preview-file/{filename}",
            "nama": "livewire.preview-file",
            "metode": "GET|HEAD"
        },
        {
            "uri": "livewire-f552b613/js/{component}.js",
            "nama": null,
            "metode": "GET|HEAD"
        },
        {
            "uri": "livewire-f552b613/css/{component}.css",
            "nama": null,
            "metode": "GET|HEAD"
        },
        {
            "uri": "livewire-f552b613/css/{component}.global.css",
            "nama": null,
            "metode": "GET|HEAD"
        },
        {
            "uri": "up",
            "nama": null,
            "metode": "GET|HEAD"
        },
        {
            "uri": "/",
            "nama": "beranda",
            "metode": "GET|HEAD"
        },
        {
            "uri": "katalog",
            "nama": "katalog",
            "metode": "GET|HEAD"
        },
        {
            "uri": "produk/{slug}",
            "nama": "produk.detail",
            "metode": "GET|HEAD"
        },
        {
            "uri": "login",
            "nama": "login",
            "metode": "GET|HEAD"
        },
        {
            "uri": "logout",
            "nama": "logout",
            "metode": "GET|HEAD"
        },
        {
            "uri": "keranjang",
            "nama": "keranjang",
            "metode": "GET|HEAD"
        },
        {
            "uri": "checkout",
            "nama": "checkout",
            "metode": "GET|HEAD"
        },
        {
            "uri": "pesanan/riwayat",
            "nama": "pesanan.riwayat",
            "metode": "GET|HEAD"
        },
        {
            "uri": "pesanan/lacak/{invoice}",
            "nama": "pesanan.lacak",
            "metode": "GET|HEAD"
        },
        {
            "uri": "pesanan/bayar/{invoice}",
            "nama": "pesanan.bayar",
            "metode": "GET|HEAD"
        },
        {
            "uri": "pesanan/faktur/{invoice}",
            "nama": "pesanan.faktur",
            "metode": "GET|HEAD"
        },
        {
            "uri": "ulasan/{pesananId}/{produkId}",
            "nama": "ulasan.buat",
            "metode": "GET|HEAD"
        },
        {
            "uri": "dashboard",
            "nama": "dashboard",
            "metode": "GET|HEAD"
        },
        {
            "uri": "admin/dashboard",
            "nama": "admin.dashboard",
            "metode": "GET|HEAD"
        },
        {
            "uri": "admin/pesanan",
            "nama": "admin.pesanan",
            "metode": "GET|HEAD"
        },
        {
            "uri": "admin/pesanan/{pesanan}",
            "nama": "admin.pesanan.detail",
            "metode": "GET|HEAD"
        },
        {
            "uri": "admin/produk",
            "nama": "admin.produk",
            "metode": "GET|HEAD"
        },
        {
            "uri": "admin/produk/tambah",
            "nama": "admin.produk.tambah",
            "metode": "GET|HEAD"
        },
        {
            "uri": "admin/produk/{id}/edit",
            "nama": "admin.produk.edit",
            "metode": "GET|HEAD"
        },
        {
            "uri": "admin/kategori",
            "nama": "admin.kategori",
            "metode": "GET|HEAD"
        },
        {
            "uri": "admin/merek",
            "nama": "admin.merek",
            "metode": "GET|HEAD"
        },
        {
            "uri": "admin/voucher",
            "nama": "admin.voucher",
            "metode": "GET|HEAD"
        },
        {
            "uri": "admin/log",
            "nama": "admin.log",
            "metode": "GET|HEAD"
        },
        {
            "uri": "admin/laporan",
            "nama": "admin.laporan",
            "metode": "GET|HEAD"
        },
        {
            "uri": "admin/pengguna",
            "nama": "admin.pengguna",
            "metode": "GET|HEAD"
        },
        {
            "uri": "admin/cms",
            "nama": "admin.cms",
            "metode": "GET|HEAD"
        },
        {
            "uri": "storage/{path}",
            "nama": "storage.local",
            "metode": "GET|HEAD"
        }
    ]
}